{
  "sidebar": [
    {
      "title": "Requesters",
      "path": "/requesters/",
      "collapsable": true,
      "sidebarDepth": 1,
      "children": [
        "/requesters/create-request",
        "/requesters/develop-client-contract"
      ]
    },
    {
      "title": "Providers",
      "path": "/providers/",
      "collapsable": true,
      "sidebarDepth": 1,
      "children": [
        "/providers/api-integrations",
        "/providers/configure-airnode",
        "/providers/deploy-airnode",
        "/providers/set-authorizers"
      ]
    },
    {
      "title": "Hackathon 2022",
      "path": "/hackathon/",
      "collapsable": true,
      "sidebarDepth": 1,
      "children": [
        "/hackathon/location"
      ]
    }
  ]
}